azure/__init__.py
azure/cli/__init__.py
azure/cli/command_modules/__init__.py
azure/cli/command_modules/servicefabric/__init__.py
azure/cli/command_modules/servicefabric/_client_factory.py
azure/cli/command_modules/servicefabric/_help.py
azure/cli/command_modules/servicefabric/_params.py
azure/cli/command_modules/servicefabric/commands.py
azure/cli/command_modules/servicefabric/custom.py
azure/cli/command_modules/servicefabric/template/linux/parameter.json
azure/cli/command_modules/servicefabric/template/linux/template.json
azure/cli/command_modules/servicefabric/template/windows/parameter.json
azure/cli/command_modules/servicefabric/template/windows/template.json
opal_azure_cli_servicefabric-0.1.22.dist-info/METADATA
opal_azure_cli_servicefabric-0.1.22.dist-info/WHEEL
opal_azure_cli_servicefabric-0.1.22.dist-info/top_level.txt
opal_azure_cli_servicefabric-0.1.22.dist-info/RECORD
