Metadata-Version: 2.1
Name: opal-azure-cli-servicefabric
Version: 0.1.22
Summary: Microsoft Azure Service Fabric Command-Line Tools
Home-page: https://github.com/Azure/azure-cli
Author: Microsoft Corporation
Author-email: azpycli@microsoft.com
License: MIT
Platform: UNKNOWN
Classifier: Development Status :: 4 - Beta
Classifier: Intended Audience :: Developers
Classifier: Intended Audience :: System Administrators
Classifier: Programming Language :: Python
Classifier: Programming Language :: Python :: 2
Classifier: Programming Language :: Python :: 2.7
Classifier: Programming Language :: Python :: 3
Classifier: Programming Language :: Python :: 3.4
Classifier: Programming Language :: Python :: 3.5
Classifier: Programming Language :: Python :: 3.6
Classifier: License :: OSI Approved :: MIT License
Requires-Dist: azure-graphrbac (==0.60.0)
Requires-Dist: azure-keyvault (==1.1.0)
Requires-Dist: azure-mgmt-network (==3.0.0)
Requires-Dist: azure-mgmt-compute (==5.0.0)
Requires-Dist: azure-mgmt-storage (==3.3.0)
Requires-Dist: azure-mgmt-servicefabric (==0.2.0)
Requires-Dist: azure-mgmt-keyvault (==1.1.0)
Requires-Dist: opal-azure-cli-core (>=2.0.68)
Requires-Dist: pyOpenSSL
Requires-Dist: azure-cli-command-modules-nspkg (>=2.0.0)
